shortcountrynames/__init__.py
shortcountrynames/_version.py
shortcountrynames-0.10.0.dist-info/LICENSE
shortcountrynames-0.10.0.dist-info/METADATA
shortcountrynames-0.10.0.dist-info/WHEEL
shortcountrynames-0.10.0.dist-info/top_level.txt
shortcountrynames-0.10.0.dist-info/RECORD
