Metadata-Version: 2.1
Name: shortcountrynames
Version: 0.10.0
Summary: Maps from two or three letter country codes to short names
Home-page: https://github.com/rgieseke/shortcountrynames
Author: Robert Gieseke
Author-email: rob.g@web.de
License: CC0
Keywords: country code
Platform: any
Classifier: Development Status :: 4 - Beta
Classifier: Intended Audience :: Developers
Classifier: Operating System :: OS Independent
Classifier: Programming Language :: Python :: 3
Classifier: Programming Language :: Python :: 3.6
Classifier: Programming Language :: Python :: 3.7
Classifier: Programming Language :: Python :: 3.8
License-File: LICENSE
